{"cast": {"0136797": "Steve Carell", "0933988": "Rainn Wilson", "1024677": "John Krasinski", "0278979": "Jenna Fischer", "1145983": "B.J. Novak", "1159180": "Ed Helms", "1534715": "Leslie David Baker", "1580911": "Brian Baumgartner", "0105588": "Creed Bratton", "0281212": "Kate Flannery", "1411676": "Mindy Kaling", "1526554": "Angela Kinsey", "1386645": "Oscar Nu\u00f1ez", "0732497": "Craig Robinson", "0809613": "Phyllis Smith", "0752407": "Amy Ryan", "2423799": "Tug Coker", "1083077": "Blake Robbins", "3573958": "Calvin Tenner"}, "geners": ["Comedy"], "runtimes": ["22"],  "plot": ["Holly is transferred back to New Hampshire after corporate discovers that she and Michael are dating. Dwight tries to apply to Cornell to get under Andy's skin. Jim's brothers and Pam decide to play a trick on Jim when they meet for lunch.", "Michael and Holly are forced to question the future of their relationship after she is transferred out of Scranton. Dwight gets on Andy's nerves by pretending to be interested in his alma mater. Pam and Jim have an awkward lunch with his brothers.\u2014Anonymous"], "genres": "N/A", "imdbID": "1248749", "rating": 7.9, "votes": 5992, "number_of_episodes": 188}