{"cast": {"1101677": "Jun Fukuyama", "0757327": "Takahiro Sakurai", "0633989": "Yukana", "0590922": "Omi Minami", "0157131": "Saeko Chiba", "1046347": "Fumiko Orikasa", "1360441": "Sayaka \u00d4hara", "1617276": "Noriaki Sugiyama", "0794230": "Tetsu Shiratori", "0409291": "Kikuko Inoue", "0535070": "Mitsuaki Madono", "1840556": "Ami Koshimizu", "0849004": "Kazunari Tanaka", "1327264": "Yasuyuki Kase", "2657351": "Ryuzo Hasuike", "0620124": "J\u00f4ji Nakata", "2344361": "Satomi Arai", "0023719": "Masuo Amada", "0847041": "Yuji Takada", "1670451": "Junko Minagawa", "0363066": "Kiyoyuki Yanada", "1242538": "Yoshiyuki K\u00f4no", "0621454": "Ken Narita", "2950682": "K\u00f4z\u00f4 Mito", "0097765": "Johnny Yong Bosch", "0063527": "Brian Beacock", "0089707": "Steve Blum", "0757929": "Deborah Sale Butler", "0218555": "John DeMita", "1063287": "Doug Erholtz", "0346410": "Kim Mai Guest", "1512156": "Kate Higgins", "2450492": "Amy Kincaid", "0512278": "Michael Lindsay", "0523180": "Yuri Lowenthal", "0569479": "Mary Elizabeth McGlynn", "1240448": "Liam O'Brien", "0528936": "Jamieson Price", "0741398": "Michelle Ruff", "1142722": "Keith Silverstein", "1886746": "Roger Craig Smith", "0422849": "Doug Stone", "1022263": "Karen Strassman", "0397364": "Julie Ann Taylor", "0861558": "Kirk Thornton", "0992184": "Travis Willingham"}, "geners": ["Animation", "Action", "Drama", "Fantasy", "Sci-Fi", "Thriller"], "runtimes": ["24"],  "plot": ["The student council of Ashford academy are taken hostage as is the Viceroy's younger sister, Lady Euphemia."], "genres": "N/A", "imdbID": "0998617", "rating": 8.4, "votes": 1512, "number_of_episodes": 54}