{"cast": {"1829595": "Greg Davies", "2640385": "Alex Horne", "6399949": "Fern Brady", "11470228": "Munya Chawawa", "7226292": "John Kearns", "3155853": "Sarah Millican", "1465223": "Dara \u00d3 Briain"}, "geners": ["Comedy", "Game-Show"], "runtimes": ["47"],  "plot": ["Dara \u00d3 Briain displays a fabulous flair for folding, Fern Brady complains about being forced to tidy up, and Munya Chawawa tries to work some DIY magic with a coat hanger."], "genres": "N/A", "imdbID": "21111238", "rating": 7.7, "votes": 162, "number_of_episodes": 182}