{
    "1": {
        "title": "The Chassis, the Wings",
        "released": "2022-09-29",
        "rating": "N/A",
        "imdb_id": "tt21109564",
        "subtitles_exists": false,
        "subtitles_full_path": ""
    },
    "2": {
        "title": "Enormous Hugeness",
        "released": "2022-10-06",
        "rating": "N/A",
        "imdb_id": "tt21111240",
        "subtitles_exists": false,
        "subtitles_full_path": ""
    },
    "3": {
        "title": "Dafty in the Middle",
        "released": "2022-10-13",
        "rating": "N/A",
        "imdb_id": "tt21111236",
        "subtitles_exists": false,
        "subtitles_full_path": ""
    },
    "4": {
        "title": "Crumbs in My Bralette",
        "released": "2022-10-20",
        "rating": "N/A",
        "imdb_id": "tt21111238",
        "subtitles_exists": false,
        "subtitles_full_path": ""
    },
    "8": {
        "title": "The One That Bats Do",
        "released": "2022-11-17",
        "rating": "N/A",
        "imdb_id": "tt21111250",
        "subtitles_exists": false,
        "subtitles_full_path": ""
    },
    "9": {
        "title": "A New Business End",
        "released": "2022-11-24",
        "rating": "N/A",
        "imdb_id": "tt21111254",
        "subtitles_exists": false,
        "subtitles_full_path": ""
    }
}