{"cast": {"1829595": "Greg Davies", "2640385": "Alex Horne", "7649398": "Lolly Adefope", "0219465": "Hugh Dennis", "0276161": "Noel Fielding", "0317329": "Mel Giedroyc", "3899396": "Joe Lycett", "6565051": "Joe Auckland", "9867793": "Mark Brown", "0614811": "Al Murray"}, "geners": ["Comedy", "Game-Show"], "runtimes": ["43"],  "plot": ["Taskmaster Greg Davies tries to spot the five camouflaged comedians before they try to herd dogs and chickens. They also have to re-home a fish and create a trailer for Taskmaster: The Movie."], "genres": "N/A", "imdbID": "6397394", "rating": 8.3, "votes": 287, "number_of_episodes": 182}