{"cast": {"1698655": "Erdal Besik\u00e7ioglu", "4245240": "Fatih Artman", "4245708": "Inan\u00e7 Konuk\u00e7u", "2667193": "Canan Erguder", "0043709": "Ege Aydan", "1855651": "Berke \u00dczrek", "4246039": "Berkan Sal", "2704055": "Seda Bakan", "4428959": "Ay\u00e7a Eren", "4245857": "Hakan Hatipoglu", "3251456": "Zeynep Koltuk", "4597034": "Eray Eserol", "1728948": "Mine Tugay", "12855421": "Sercan Boztepe"}, "geners": ["Crime", "Drama", "Mystery", "Thriller"], "runtimes": 0,  "plot": ["While examining the body of an unidentified man found in a lake, Ghost sees an embroidered monogram that triggers childhood memories."], "genres": "N/A", "imdbID": "2191969", "rating": 7.8, "votes": 116, "number_of_episodes": 105}