{"cast": {"0000867": "Jason Bateman", "0005577": "Portia de Rossi", "0004715": "Will Arnett", "0148418": "Michael Cera", "0790057": "Alia Shawkat", "0355024": "Tony Hale", "0189144": "David Cross", "0001787": "Jeffrey Tambor", "0910055": "Jessica Walter", "0001857": "Henry Winkler", "0000551": "Dermot Mulroney", "0175814": "Frances Conroy", "0005443": "Jean Smart", "0051469": "Maria Bamford", "3324982": "Kyle Mooney", "0453115": "Taran Killam", "1130627": "Cobie Smulders", "4564958": "Thomas Barbusca", "6236783": "Owen Vaccaro", "4347315": "Steele Stebbins", "0005498": "Concetta Tomei", "1568793": "Sophi Bairley", "2167350": "B.J. Bales", "2048735": "Todd Aaron Brotze", "0114383": "P.L. Brown", "1167794": "Jessica St. Clair", "1451905": "Fred Cross", "4078498": "Erin Helm", "2654402": "Will Hines", "0415688": "David Jahn", "6277120": "Savannah Kennick", "0910563": "Monnae Michaell", "1506981": "Bashir Salahuddin", "0591485": "Liza Minnelli", "10598621": "Janise Anthony", "0000165": "Ron Howard", "4861659": "Hayden Szeto"}, "geners": ["Comedy"], "runtimes": ["28"],  "plot": ["As the trial kicks off, the Guilty Guys throw the family for a loop. Lucille learns surprising news about Dusty. George-Michael plots a distraction."], "genres": "N/A", "imdbID": "4861490", "rating": 6.6, "votes": 835, "number_of_episodes": 84}