{"cast": {"0001349": "Jennifer Love Hewitt", "0175633": "David Conrad", "2324912": "Christoph Sanders", "0005085": "Jamie Kennedy", "0005179": "Camryn Manheim", "1140666": "Patrick J. Adams", "0642259": "Michael O'Neill", "0337965": "Jenna Leigh Green", "0388064": "Edwin Hodge", "1555781": "Linara Washington", "0479779": "Patrick Labyorteaux", "1058987": "Kenneth Mitchell", "1434786": "Debbie Campbell", "0835895": "Jeffrey Stubblefield", "1865193": "Brandon Killham", "1536169": "Patrick Weil"}, "geners": ["Drama", "Fantasy"], "runtimes": ["44"],  "plot": ["The appearance of a paranormal investigator at a neighbor's house draws Melinda and Eli into investigating the mysterious disappearance of the house's previous owner. And disrupts Melinda's plans to reveal her gift to Sam."], "genres": "N/A", "imdbID": "1256151", "rating": 7.7, "votes": 246, "number_of_episodes": 107}