{"cast": {"1102891": "Kristen Schaal", "0728762": "Jason Ritter", "3229215": "Alex Hirsch", "0048389": "Dee Bradley Baker", "1480095": "Matt Chapman", "0004802": "Linda Cardellini", "1584992": "Keith Ferguson", "0287182": "Will Forte", "5106831": "Michael Rianda", "0724656": "Kevin Michael Richardson", "0877203": "Gregg Turkington", "3006131": "Thurop Van Orman"}, "geners": ["Animation", "Adventure", "Comedy", "Family", "Fantasy"], "runtimes": ["22"],  "plot": ["It's the hottest day of the Summer and the opening day of the Gravity Falls pool, where Mabel befriends a mysterious boy named Mermando.", "It's the hottest day of the summer in Gravity Falls, and the new Gravity Falls Pool is now open. Mabel falls in love with a mysterious boy named Mermando who turns out to be a merman and needs her help so that he can see his family. Meanwhile, Dipper got the job of assistant lifeguard to impress Wendy and Stan fights with Lil' Gideon for the best seat at the pool.\u2014Anonymous"], "genres": "N/A", "imdbID": "2717562", "rating": 7.6, "votes": 3672, "number_of_episodes": 41}