{"cast": {"0165087": "Jeremy Clarkson", "1414369": "Richard Hammond", "0561982": "James May", "2247190": "Ben Collins", "0429809": "Katie Price", "3630139": "Luca Badoer"}, "geners": ["Adventure", "Comedy", "Sport", "Talk-Show"], "runtimes": ["51"],  "plot": ["The boys are given 100 pounds each to buy cars that costs less than 100 pounds. Once they have purchase the car of their choice, they are given a number of challenges. Richard road test a muscle car that he want to buy, the 1968 Dodge Charger 440 R/T. Jeremy road tests 2 lightweight supercars, the Porsche 911 GT3 RS and the Ferrari 360 Challenge Stradale.\u2014Caboose"], "genres": "N/A", "imdbID": "0729690", "rating": 8.0, "votes": 281, "number_of_episodes": 328}