{"cast": {"2322250": "Makoto Furukawa", "5481013": "Kaito Ishikawa", "0648768": "Masaya Matsukaze", "2976492": "Aoi Y\u00fbki", "2977461": "Saori Hayami", "1697606": "Y\u00fbichi Nakamura", "0395950": "S\u00f4ichir\u00f4 Hoshi", "0586528": "Shin'ichir\u00f4 Miki", "5256487": "Hiromichi Tezuka", "8060552": "Shinsuke Sugawara", "1054043": "Atsushi Ono", "0468729": "Takehito Koyasu", "8034028": "Natsumi Fujiwara", "4896133": "Y\u00fbya Murakami", "4896011": "Naoya Nosaka", "6589706": "Itaru Yamamoto", "1851676": "Tar\u00f4 Yamaguchi", "2961464": "K\u00f4ichi S\u00f4ma", "8934294": "Hayato Fujii", "2386242": "Ry\u00f4 Sugisaki", "1938624": "Y\u00f4ji Ueda", "5489754": "Max Mittelman", "6450743": "Zach Aguilar", "0283253": "Wendee Lee", "0861558": "Kirk Thornton", "4048190": "Alan Lee", "3677958": "Laura Post", "6770060": "Bill Butts", "5097979": "Armen Taylor", "5650061": "Joe Zieja", "1408690": "Ben Pronsky", "2103271": "Corina Boettger", "0590235": "Bill Millsap", "7325686": "Andrew Russell", "1365137": "Patrick Seitz", "1727087": "Brook Chalmers", "0726184": "Sam Riegel", "3803047": "Chris Tergliafera", "7751721": "Christian La Monte", "4645694": "Jason Marnocha", "7429639": "Jeannie Tirado", "1035500": "Kyle Hebert", "2837894": "Robbie Daymond", "0469674": "Steve Kramer", "1821497": "Steve Prince", "1063287": "Doug Erholtz", "2859742": "Brock Powell", "6981965": "Kellen Goff", "1920556": "Todd Haberkorn", "7112121": "Jonah Scott", "2099549": "Arnie Pantoja", "5168315": "Sean Chiplock", "1075459": "Bill Rogers", "3119972": "Lauren Landa", "4588329": "Jackie Lastra", "10634044": "Tiffany Oliver", "9368358": "Breaugh Olson", "7057100": "Zachary T. Rice", "3033661": "Alex J. Dean"}, "geners": ["Animation", "Action", "Comedy", "Fantasy", "Sci-Fi"], "runtimes": ["23"],  "plot": ["Saitama continues facing opponents in the tournament. Genos receives a stress signal depicting that there are 5 monsters in City C and goes to kill them. Blizzard tries to fight a monster but she turns out be very strong.", "The Super Fight tournament kicks off while Genos takes on multiple monsters who have appeared in City C. Elsewhere, countless monsters are wreaking havoc in multiple areas, but the Hero Association is being overwhelmed by the sheer number of threats."], "genres": "N/A", "imdbID": "10050336", "rating": 7.5, "votes": 2371, "number_of_episodes": 39}