{"cast": {"0780435": "Ryan Seacrest", "0001014": "Mariah Carey", "1193098": "Randy Jackson", "3747326": "Nicki Minaj", "1236707": "Keith Urban", "5471970": "Lazaro Arbos", "4352550": "Janelle Arthur", "2641253": "Daniel Bateman", "5319213": "Camille Blouin", "2564139": "Brian Brigham", "3610514": "Brian Corsetti", "4526533": "Clifton Duffin Jr.", "4511150": "Matheus Fernandes", "5085923": "Curtis Finch Jr.", "5984004": "Peter Frank", "5086206": "Candice Glover", "2748605": "Kree Harrison", "5560955": "Amber Holcomb", "5533571": "Brandy Hotard", "5560994": "Paul Jolley", "5560967": "Angie Miller", "5533472": "Megan Miller", "3755339": "Kc Monnie", "3859501": "Lance Paul", "5571735": "Jarett Shorts", "5560969": "Burnell Taylor", "0860465": "Mark Thompson", "5560984": "Devin Velez", "0893501": "Ken Waters", "5313950": "Wayne Xia", "6937130": "Patrick Blood"}, "geners": ["Documentary", "Game-Show", "Music", "Reality-TV"], "runtimes": 0,  "plot": "N/A", "genres": "N/A", "imdbID": "2902356", "rating": 4.5, "votes": 35, "number_of_episodes": 732}