{"cast": {"0556387": "Corinne Masiero", "0001461": "Virginie Ledoyen", "0201151": "Florence Darel", "0521051": "Jean-Pierre Lorit", "7028122": "L\u00e9a Lopez", "1958488": "Ralph Amoussou", "1712515": "Paul Kircher", "0697683": "Marco Prince", "0818686": "Jacques Spiesser", "4921704": "Maxence Vandevelde", "0516582": "Jean-Louis Loca", "7524117": "Bryan Tr\u00e9sor", "11607423": "Nicolas de Vipart", "0723796": "Firmine Richard", "0551791": "Jacques Martial", "13445195": "Serge Pr\u00e9sident", "11607422": "\u00c9lodie Auster", "14841220": "Alexandre Ceva", "9736500": "Allison Guiougou", "9259081": "N'Dy Thomas", "3068496": "Murielle Hilaire", "11607426": "C\u00e9dric Jean-Pierre", "11607424": "Maxime Dulice", "13507925": "Dominique Dupont"}, "geners": ["Comedy", "Crime", "Drama", "Mystery"], "runtimes": ["93"],  "plot": ["Marleau's sweet vacation in Guadaloupe gets interrupted when she's called to help the local police.", "The slave tree: Marleau is holidaying in Guadeloupe, a chance to catch up with an old friend, Lo\u00efc. Her peace and quiet doesn't last long when a musician is murdered in a club. Lending the local police a hand, she takes a close interest in the last people to see the victim alive.\u2014TV5Monde Europe"], "genres": "N/A", "imdbID": "11115888", "rating": 6.6, "votes": 44, "number_of_episodes": 36}