{"cast": {"10205992": "Shane McNair", "2676147": "Jonathan Groff", "0564697": "Holt McCallany", "1653125": "Albert Jones", "5651486": "Christopher Livingston", "7155000": "Darrin Giossi", "1306344": "Stacey Roca", "4191492": "Euseph Messiah", "9341850": "Zachary Scott Ross", "0062682": "Beau Baxter", "0518547": "June Carryl", "2648933": "Nick Choksi", "3293435": "Myles Cranford", "1501501": "Alton Fitzgerald White", "3239528": "Rita Gregory", "3495436": "Trey Teufel", "1382564": "Dohn Norwood", "2057826": "Sierra Aylina McClain", "1090591": "Allie McCulloch", "1422348": "Andy S. Allen", "0125797": "Brian Byers", "7290078": "Rich Morrow", "10920451": "Matt Ruffo", "1332395": "Sean Cullen", "1167931": "Circus-Szalewski", "0186883": "Logan Crawford", "0205318": "Regi Davis", "3111477": "Amaris Davidson", "1409996": "Emily Berry", "0148964": "Michael Cerveris", "0930617": "Gareth Williams", "3410713": "Siovhan Christensen", "2802243": "Crystal Lee Brown", "1396022": "Anna Torv", "8387726": "Mark Pettit", "0668262": "Ashlee Payne", "3171185": "Sonny Valicenti", "10364081": "Shelly Lynn Koch", "9986552": "Morgan Miller", "1395385": "Vernon Keith Ruffin Jr."}, "geners": ["Crime", "Drama", "Mystery", "Thriller"], "runtimes": ["73"],  "plot": ["The investigation zeroes in on a prime suspect who proves adept at manipulating a volatile situation to his advantage."], "genres": "N/A", "imdbID": "10731012", "rating": 8.7, "votes": 6234, "number_of_episodes": 19}