{"cast": {"0799619": "John Simmit", "0806760": "Nikky Smedley", "0266623": "Pui Fan Lee", "0926253": "Tim Whitnall", "0808709": "Jessica Smith", "0373472": "Mark Heenehan", "0843059": "Eric Sykes", "0929679": "Toyah Willcox"}, "geners": ["Family", "Fantasy", "Musical"], "runtimes": ["12"],  "plot": ["Teletubbies Original: Andy Brown and some children visit and aquarium to learn how things swim in the water. The Teletubbies play an in and out game when a cloud appears in Teletubbyland."], "genres": "N/A", "imdbID": "0868730", "rating": 4.9, "votes": 18, "number_of_episodes": 389}