{"cast": {"1047343": "Chris Harrison", "6141802": "Andi Dorfman", "6492780": "Nick Viall", "6492790": "Andrew Poole", "6492783": "Marcus Grodd", "6492791": "Bradley Wisk", "6492781": "Patrick Jagodzinski", "6492778": "Brian Osborne", "6492779": "Marquel Martin", "6448903": "Eric Hill", "6492784": "Josh Murray", "6492789": "Cody Sattler", "6492794": "Ron Worrell", "6492782": "Tasos Hernandez", "6492786": "Dylan Pettit", "6492787": "J.J. O'Brien", "6492788": "Chris Soules", "6492785": "Brett Melnick", "1349841": "Boyz II Men"}, "geners": ["Game-Show", "Reality-TV", "Romance"], "runtimes": ["86"],  "plot": ["Andi hits the road with her 16 remaining bachelors to the beautiful coastal city of Santa Barbara, California. Nick V., who has had his share of doubts about this journey, will get a chance to ease his worries on a day-long tour of the city with Andi. Twelve guys get the date of a lifetime when they discover they will be singing with R&B icons BOYZ II MEN, but are stunned to find out it will be in front of a live concert audience. JJ and Andi take a leap into the very far future when they are turned into a sweet 80-year-old couple by Hollywood makeup artists and proceed to fool the Santa Barbara citizens. Meanwhile, one bachelor receives devastating news that brings his search for love to a halt -- how will Andi react? And a major confrontation between some of the men brings questions about whether one of them is here just for a good time.\u2014Anonymous"], "genres": "N/A", "imdbID": "3756532", "rating": 5.3, "votes": 15, "number_of_episodes": 238}