{"cast": {"0013037": "Shohreh Aghdashloo", "1204760": "Kevin Alejandro", "1987941": "Krizia Bajos", "1072611": "JB Blanc", "5077468": "Miles Brown", "10411245": "Faustino Duran", "9768698": "Molly Harris", "3600780": "Remy Hii", "5257564": "Mia Sinclair Jenness", "5235708": "Mara Junot", "0005079": "Josh Keaton", "6949652": "Erica Lindbeck", "0516003": "Harry Lloyd", "0523180": "Yuri Lowenthal", "1731499": "Abigail Marlowe", "2022559": "Dave B. Mitchell", "1252685": "Toks Olagundoye", "1886746": "Roger Craig Smith", "1032853": "Jason Spisak", "2794962": "Hailee Steinfeld", "0851317": "Fred Tatasciore", "0875810": "Brett Tucker", "2722066": "Amirah Vann", "1964186": "Mick Wingert", "0235261": "Terri Douglas", "0235960": "Robin Atkin Downes", "0579914": "Scott Menville", "5620984": "Arthur Ortiz", "1719288": "Marcella Lentz-Pope", "0842303": "Shane Sweet", "1312566": "Kari Wahlgren"}, "geners": ["Animation", "Action", "Adventure", "Drama", "Fantasy", "Sci-Fi"], "runtimes": ["41"],  "plot": ["Idealistic inventor Jayce attempts to harness magic through science --- despite his mentor's warning. Criminal kingpin Silco tests a powerful substance.", "Jayce, a Piltover student, is expelled for arcane research after a near-death experience. Viktor, a disabled scientist, offers to help him continue his forbidden work. In Zaun, Vander faces pressure to fight Piltover, while Vi surrenders herself, and Silco manipulates Deckard into consuming a dangerous substance.\u2014Oscar Serpa"], "genres": "N/A", "imdbID": "15496380", "rating": 8.5, "votes": 33244, "number_of_episodes": 18}