{"cast": {"0000330": "Stockard Channing", "0384211": "Dul\u00e9 Hill", "0005049": "Allison Janney", "0539651": "Joshua Malina", "0005203": "Mary McCormack", "0597223": "Janel Moloney", "0771493": "Richard Schiff", "0817983": "John Spencer", "0925966": "Bradley Whitford", "0000640": "Martin Sheen", "0000257": "Alan Alda", "0155693": "Kristin Chenoweth", "0170550": "Gary Cole", "0642145": "Ed O'Neill", "0422710": "Penn Jillette", "0854418": "Teller", "0005253": "Elisabeth Moss", "0005316": "Mary Kay Place", "0133474": "Ron Canada", "0112070": "Stanley Kamel", "0732947": "NiCole Robinson", "0261729": "Ren\u00e9e Estevez", "0205685": "Timothy Davis-Reed", "0614449": "Kris Murphy", "0614845": "Ben Murray", "1497570": "Paul Rae", "0469674": "Steve Kramer", "0182620": "Tracey Costello", "0440066": "Elizabeth Karr", "0789231": "James Sharpe", "2048220": "Brian Ceponis", "12827017": "Gorja Max", "2048484": "Ken Weiner"}, "geners": ["Drama"], "runtimes": ["43"],  "plot": ["Magicians Penn and Teller give a controversial performance at Zoey's birthday party in the White House that threatens to drown out the news of the impending China trip. President Bartlet goes to New Orleans on his way to China after unexpectedly requesting briefings be postponed until they are in the air. Josh tries to decide which Democratic presidential candidate he wants to support, and is alarmed that Bartlet wants to appoint California Republican Senator Arnold Vinick to be Ambassador to the United Nations.\u2014Murray Chapman"], "genres": "N/A", "imdbID": "0745638", "rating": 8.3, "votes": 733, "number_of_episodes": 155}