{"cast": {"0000098": "Jennifer Aniston", "0001073": "Courteney Cox", "0001435": "Lisa Kudrow", "0001455": "Matt LeBlanc", "0001612": "Matthew Perry", "0001710": "David Schwimmer", "0005016": "Alexandra Holden", "0655963": "Scott Paetty", "0447963": "Chris Kennedy", "0185104": "Josh Coxx", "0072824": "Jim Bentley", "1711051": "Hunter Cochran", "3208716": "Billy Dec", "0878837": "James Michael Tyler"}, "geners": ["Comedy", "Romance"], "runtimes": ["22"],  "plot": ["Joey tries to get everyone to pay for his broken fridge. Ross becomes paranoid when Elizabeth makes plans for spring break. Monica and Chandler compete against Phoebe to find Rachel a date.", "Joey's fridge is broken and he tries to get everyone to pay for his fridge. Rachel is looking for a date for a charity ball and Phoebe, Chandler and Monica look for a guy. Phoebe finds a guy and Chandler and Monica find one so they have a big competition to get Rachel pick their guy. Joey has to eat all his food because the fridge is gone. Ross mistakenly thinks that Elizabeth wants to go on a trip with him and is very relieved when she only wants to tell him that she's going on Spring vacation with her friends. But when Ross realizes that she is going to party a lot and probably meet other guys he freaks out. Rachel is really upset about the competition between Monica/Chandler and Phoebe about her date for the ball so she decides to go alone and has a great time. Ross ends up going to Florida with Elizabeth to prevent her from meeting other guys.\u2014Anonymous"], "genres": "N/A", "imdbID": "0583526", "rating": 8.1, "votes": 4987, "number_of_episodes": 235}