{"cast": {"0144657": "Dan Castellaneta", "0001413": "Julie Kavner", "0004813": "Nancy Cartwright", "0810379": "Yeardley Smith", "0000279": "Hank Azaria", "0733427": "Harry Shearer", "0005078": "Stacy Keach", "0370788": "Pamela Hayden", "0440885": "John Kassir", "0534134": "Tress MacNeille", "0853122": "Russi Taylor", "0927293": "Karl Wiedergott"}, "geners": ["Animation", "Comedy"], "runtimes": ["30"],  "plot": ["Homer throws out Santa's Little Helper for not saving him from a fire, but soon the dog becomes Duff's new mascot.", "After Santa's Little Helper fails to save Homer in a fire,he plans to get rid of the dog but after a journalist sees Santa's Little Helper play with a beer can he becomes the new mascot of Duff Beer - and,given his new fame,his original owner claims him back. A publicity stunt is arranged at the beach whereby Santa's Little Helper will save Homer from a shark but again he fails so the shark is made the new Duff mascot instead. The owner now wants rid of the dog so the Simpsons take him back.\u2014don @ minifie-1"], "genres": "N/A", "imdbID": "0701193", "rating": 6.6, "votes": 1735, "number_of_episodes": 848}