{"cast": {"0144657": "Dan Castellaneta", "0001413": "Julie Kavner", "0004813": "Nancy Cartwright", "0810379": "Yeardley Smith", "0000279": "Hank Azaria", "0733427": "Harry Shearer", "0408284": "Michael Imperioli", "0001505": "Joe Mantegna", "0004987": "Kirk Hammett", "0381723": "James Hetfield", "0582376": "Metallica", "0005515": "Lars Ulrich", "0874235": "Robert Trujillo", "0001592": "Joe Pantoliano", "0370788": "Pamela Hayden", "0534134": "Tress MacNeille", "0853122": "Russi Taylor", "0927293": "Karl Wiedergott"}, "geners": ["Animation", "Comedy"], "runtimes": ["21"],  "plot": ["When Fat Tony has to take a time-out due to a whacking attempt, Homer and Bart take over the business.", "The laughing kid of the school kids' car pool, Michael, is all of a sudden feared by everyone when it comes out that he is the son of local mob boss (or, as he says, \"garbage businessman\") Fat Tony. Everyone but Lisa. She tries to get to know him and finds out all he really wants to do is becoming a chef, cooking being his greatest passion. When Fat Tony is severely hurt by a whacking attempt, carried out by a rival mob considering him vulnerable for his son won't take revenge in case of his death, Michael doesn't feel like he can take over the family business. So Homer and Bart, feeling responsible for the new friends of the family, offer to take over while Fat Tony is recovering.\u2014jaggermick66"], "genres": "N/A", "imdbID": "0831239", "rating": 7.5, "votes": 2028, "number_of_episodes": 848}