{"cast": {"0000213": "Winona Ryder", "1092086": "David Harbour", "6016511": "Finn Wolfhard", "5611121": "Millie Bobby Brown", "7140802": "Gaten Matarazzo", "5160895": "Caleb McLaughlin", "3034501": "Natalia Dyer", "6390427": "Charlie Heaton", "0120648": "Cara Buono", "0000546": "Matthew Modine", "0159609": "Joe Chrest", "6564737": "Joe Keery", "1726032": "Rob Morgan", "0664061": "Ross Partridge", "7684864": "Shannon Purser", "6324745": "John Reynolds", "6907855": "Noah Schnapp", "0825209": "Mark Steger", "2884388": "Chris Sullivan", "2409723": "Stefanie Butler", "0245486": "David Dwyer", "0245696": "Catherine Dyer", "1670129": "Randy Havens", "0420564": "Tobias Jelinek", "0442107": "Charles Lawlor", "3869592": "Bethany Anne Lind", "7635825": "Anniston Price", "6018251": "Tinsley Price", "4231366": "Chester Rushing", "3091904": "Susan Shalhoub Larkin", "3571720": "Chelsea Talmadge", "5580827": "Robert Walker Branchaud", "7591401": "Owen Beam", "7008538": "Stephen Dean", "7333458": "Isabel Chanel Freeman", "6864585": "Shelby Christine Freeman", "7168982": "Jim Heard", "4239141": "Walter Hendrix III", "1739959": "John Archer Lundgren", "7718824": "Jaxon McHan", "7892160": "Max Perethian", "7940199": "Brady Rogers", "0767499": "Leticia Sabater"}, "geners": ["Drama", "Fantasy", "Horror", "Mystery", "Sci-Fi", "Thriller"], "runtimes": ["55"],  "plot": ["Lucas, Mike and Dustin try to talk to the girl they found in the woods. Meanwhile, Hopper questions an anxious Joyce about an unsettling phone call.", "As Will is still missing, Mike, Dustin, and Lucas hide the girl in Mike's house and questions if she knows anything relative to Will's disappearance; Joyce makes contact with the police when she receives a strange phone call; Nancy and Barb attend Steve's party."], "genres": "N/A", "imdbID": "4593122", "rating": 8.4, "votes": 26034, "number_of_episodes": 42}