{"cast": {"1002609": "Nicholas Braun", "0004051": "Brian Cox", "0001085": "Kieran Culkin", "0231436": "Dagmara Dominczyk", "0295334": "Peter Friedman", "4419771": "Justine Lupe", "0532193": "Matthew Macfadyen", "0711058": "David Rasche", "0001688": "Alan Ruck", "0810397": "J. Smith-Cameron", "3512758": "Sarah Snook", "0001770": "Fisher Stevens", "0834989": "Jeremy Strong", "1573892": "Arian Moayed", "0000342": "James Cromwell", "0075588": "Jeannie Berlin", "0726200": "Peter Riegert", "0004778": "Adrien Brody", "0204706": "Hope Davis", "2592482": "Scott Nicholson", "2925225": "Zoe Winters", "0683978": "Larry Pine", "8943180": "Juliana Canfield", "3705886": "Jihae", "6221606": "Dasha Nekrasova", "7711988": "Swayam Bhatia", "1113773": "Patch Darragh", "3252039": "KeiLyn Durrel Jones", "1600051": "John Rue", "3075366": "Wayne Pyle", "7233807": "Hermione Lynch", "1975566": "Trian Long Smith", "0288214": "Alexandra Foucard", "8229129": "John F. Higgins", "1851034": "Brian Hotaling", "3204137": "Zachary James", "13083626": "Dave Granholm", "10114726": "Mitchell Hochman", "5382549": "Marvin Johnson", "9216623": "Bob Leszczak", "5677013": "Alexandra Lopez Galan", "9369511": "Seby X. Martinez", "2550538": "Matthew T. Reynolds", "2689366": "Stephen Sherman", "10050447": "Jonathan Sienkiewicz"}, "geners": ["Comedy", "Drama"], "runtimes": ["61"],  "plot": ["Kendall and the Waystar team find themselves working together at the annual shareholders' meeting, where Logan's health takes a turn."], "genres": "N/A", "imdbID": "14163702", "rating": 9.0, "votes": 8995, "number_of_episodes": 39}