{"cast": {"0372176": "Lena Headey", "0215281": "Thomas Dekker", "1132359": "Summer Glau", "0429114": "Richard T. Jones", "0907427": "Sonya Walger", "0024593": "Tony Amendola", "1883803": "Jesse Garcia", "1859475": "Omid Abtahi", "1501388": "Sasha Roiz", "1838070": "Jonathan Sadowski", "0935921": "Dean Winters", "0020327": "Brian Atkinson", "1929670": "Ambrit Millhouse", "2835196": "Sabrina P\u00e1ez", "0924277": "John Henry Whitaker", "0928991": "Lisa Wilhoit", "0050737": "Edoardo Ballerini", "1989533": "Aldo Gonzalez", "1699451": "Danielle Lozeau", "0566157": "Matt McColm", "1904326": "Mario Orozco"}, "geners": ["Action", "Drama", "Fantasy", "Sci-Fi", "Thriller"], "runtimes": ["44"],  "plot": ["John goes stir-crazy when he's confined to the house, Sarah looks up an old friend for some help, but she may face betrayal, and Cromartie begins reassembling himself.", "Having jumped forward in time to 2007, Sarah, John, and Cameron are lying low until they can arrange for false identities. Sarah visits an old friend, Enrique, who once was an expert at creating false identities but he has given up that business to his nephew. Unknown to Sarah is that he has taken up other interests. Despite his mother's insistence that he stay in the house, John goes exploring and visits his mother's old boyfriend, Charley Dixon. Cameron also tells Sarah another very good reason why the jump forward in time was necessary.\u2014garykmcd"], "genres": "N/A", "imdbID": "1055790", "rating": 7.4, "votes": 1408, "number_of_episodes": 31}