{
    "2": {
        "title": "Inspection Day/Tail Fail",
        "released": "2013-01-17",
        "rating": "N/A",
        "imdb_id": "tt2736034",
        "subtitles_exists": false,
        "subtitles_full_path": ""
    },
    "3": {
        "title": "Bro to Bro/Trick or Trixie",
        "released": "2013-01-24",
        "rating": "N/A",
        "imdb_id": "tt2736046",
        "subtitles_exists": false,
        "subtitles_full_path": ""
    },
    "4": {
        "title": "My Dad-Bot, the Doom-Bot/Monkey Mitts!",
        "released": "2013-01-31",
        "rating": "2.9",
        "imdb_id": "tt2736052",
        "subtitles_exists": false,
        "subtitles_full_path": ""
    },
    "5": {
        "title": "Not Lord Peel!/Once Upon a Monkey",
        "released": "2013-02-07",
        "rating": "N/A",
        "imdb_id": "tt2736076",
        "subtitles_exists": false,
        "subtitles_full_path": ""
    },
    "7": {
        "title": "Tail of the Unexpected/Golden Nugglets",
        "released": "2013-02-21",
        "rating": "N/A",
        "imdb_id": "tt2952016",
        "subtitles_exists": false,
        "subtitles_full_path": ""
    },
    "9": {
        "title": "When Garbage Revolts/Monkeys vs. Gorillas",
        "released": "2013-03-14",
        "rating": "N/A",
        "imdb_id": "tt2798384",
        "subtitles_exists": false,
        "subtitles_full_path": ""
    },
    "23": {
        "title": "Squidsgiving/Rocket Mommy",
        "released": "2014-03-12",
        "rating": "N/A",
        "imdb_id": "tt4270778",
        "subtitles_exists": false,
        "subtitles_full_path": ""
    }
}