{"cast": {"4485818": "Cliff Barackman"}, "geners": ["Documentary", "Drama", "Thriller"], "runtimes": ["43"],  "plot": ["The team travels to Connecticut to investigate video footage of a possible Bigfoot captured by a mother recording her children at play. In one of the most populated state per square mile, they meet with local eyewitnesses and set up a bait trap in hopes of luring in any hungry Bigfoots nearby.\u2014Anonymous"], "genres": "N/A", "imdbID": "2769294", "rating": 8.4, "votes": 15, "number_of_episodes": 93}