{"cast": {"0621788": "Niecy Nash", "0005278": "Jerry O'Connell", "0822784": "Molly Stanton", "0272479": "Jesse Tyler Ferguson", "1066346": "Jolene Purdy", "2002649": "Dave Franco", "1794258": "Ren\u00e9 Alvarado", "3121988": "Connor Barrett", "1543157": "Taylor Cole", "5865620": "Pontus Duvsj\u00f6", "2343444": "Brando Eaton", "1113895": "Joe Egender", "4117328": "Adan Iracheta", "2338560": "Aaron Jay Kenny", "0477252": "Crystal Kwon", "0498165": "RonReaco Lee", "0832688": "David Storrs", "1249901": "May Wang", "2569595": "Leila Yavari", "3767820": "Halimah Iman"}, "geners": ["Comedy"], "runtimes": ["22"],  "plot": ["A magazine article about promiscuity at the Inn leads Rhonda to crack down on Neal's antics.", "When a gossip magazine prints an anonymous article about sex in the workplace concerning a supervisor at the Inn, Rhonda and the others jump to the conclusion that Neal is the unnamed employee. Rhonda arranges for sexual-harassment training for her staff, but soon discovers that practicing what she preaches isn't that easy.\u2014Ron Kerrigan <mvg@whidbey.com>"], "genres": "N/A", "imdbID": "1145939", "rating": 4.4, "votes": 27, "number_of_episodes": 13}