{"cast": {"0688132": "Amy Poehler", "0429069": "Rashida Jones", "0773973": "Paul Schneider", "2106637": "Aziz Ansari", "0644406": "Nick Offerman", "2201555": "Aubrey Plaza", "0695435": "Chris Pratt", "1477070": "Alison Becker", "1587813": "Steve Zissis", "0641389": "Jim O'Heir", "0802876": "Retta"}, "geners": ["Comedy"], "runtimes": ["21"],  "plot": ["Leslie gets a newspaper reporter to do a story about her and the park idea, but becomes upset when she finds out that the reporter slept with Mark."], "genres": "N/A", "imdbID": "1366780", "rating": 7.1, "votes": 3510, "number_of_episodes": 124}