{"cast": {"3080119": "Lorenzo Richelmy", "0938950": "Benedict Wong", "0001040": "Joan Chen", "0269419": "Pierfrancesco Favino", "0950935": "Rick Yune", "0950620": "Ron Yuan", "3600780": "Remy Hii", "4356709": "Zhu Zhu", "0943179": "Tom Wu", "2054113": "Mahesh Jadu", "2138746": "Olivia Cheng", "2263791": "Claudia Kim", "5937328": "Uli Latukefu", "0150926": "Jacqueline Chan", "1422236": "Leonard Wu", "3616779": "Chris Pang", "1977856": "Chin Han", "0000706": "Michelle Yeoh", "3276047": "Jaime Chew", "4437269": "Esther Low", "5670511": "Laura Prats", "6977245": "Max Kellady", "0950687": "Ozzie Yue", "0407033": "Togo Igawa", "4089109": "Cha-Lee Yoon", "0921004": "Nick Dong-Sik", "1212366": "Takako Akashi"}, "geners": ["Action", "Adventure", "Drama", "History"], "runtimes": ["56"],  "plot": ["Kaidu's ruthlessness reaches new levels in his bid for power, while Hundred Eyes' former lover has him questioning his loyalties."], "genres": "N/A", "imdbID": "5137972", "rating": 8.0, "votes": 780, "number_of_episodes": 20}