{"cast": {"2552034": "Melissa Benoist", "1419635": "Mehcad Brooks", "0500200": "Chyler Leigh", "2921091": "Jeremy Jordan", "0362873": "David Harewood", "0001222": "Calista Flockhart", "0001002": "Dean Cain", "1564087": "Jenna Dewan", "0000644": "Helen Slater", "2694584": "Brit Morgan", "5844090": "Malina Pauli Weissman", "3085284": "Jay Jackson", "6491351": "Jordana Taylor", "6468283": "Michael Mealor", "1176834": "Tom Waite", "1736744": "Yuliya Rudina", "0107241": "Troy Brenna"}, "geners": ["Action", "Adventure", "Drama", "Sci-Fi"], "runtimes": ["43"],  "plot": ["Kara's foster mother visits for Thanksgiving, while an accident transforms a volatile CatCo employee into Livewire."], "genres": "N/A", "imdbID": "4955280", "rating": 7.3, "votes": 3247, "number_of_episodes": 126}