{"cast": {"2552034": "Melissa Benoist", "0500200": "Chyler Leigh", "2692146": "Katie McGrath", "2042776": "Jesse Rath", "7414233": "Nicole Maines", "2384954": "Azie Tesfai", "2255698": "Andrea Brooks", "1194672": "Julie Gonzalo", "7047874": "Staz Nair", "0362873": "David Harewood", "0001083": "Jon Cryer", "2921091": "Jeremy Jordan", "2338716": "Sarwan Badesha", "11101307": "Brian Dudley", "8513051": "Kelten Jensen", "12001057": "I Aytug", "11292874": "Rex Pai"}, "geners": ["Action", "Adventure", "Drama", "Sci-Fi"], "runtimes": ["42"],  "plot": ["Winn Schott returns from the future just as Supergirl is pursuing a Toyman copycat."], "genres": "N/A", "imdbID": "10468286", "rating": 6.7, "votes": 1708, "number_of_episodes": 126}