{"cast": {"0646241": "Craig Olejnik", "0809049": "Lauren Lee Smith", "1338828": "Ennis Esmer", "1773454": "Myl\u00e8ne Dinh-Robic", "0824220": "Peter Stebbings", "0390285": "Kris Holden-Ried", "0818166": "Tara Spencer-Nairn", "0290478": "Rainbow Sun Francks", "0093380": "Christopher Bolton", "0052925": "Matt Baram", "0233027": "Martin Donovan", "1538339": "Troy Blundell", "1384498": "James Collins", "3848496": "Janet Porter", "1272908": "Sabryn Rock", "1571018": "Gavin Fox", "1690652": "Naomi Snieckus", "3577098": "Emily Alatalo", "1219099": "Kathy Maloney"}, "geners": ["Crime", "Drama", "Fantasy", "Sci-Fi"], "runtimes": ["42"],  "plot": ["Working his first official investigation, Toby must contend with Alvin Klein's skepticism and personal agenda in solving a decade-old murder."], "genres": "N/A", "imdbID": "2091159", "rating": 7.6, "votes": 85, "number_of_episodes": 65}