{"cast": {"0009716": "Kirk Acevedo", "0015382": "Adewale Akinnuoye-Agbaje", "0001368": "Ernie Hudson", "0455767": "Terry Kinney", "0001549": "Rita Moreno", "0674782": "Harold Perrineau", "0799777": "J.K. Simmons", "0855564": "Lee Tergesen", "0907708": "Eamonn Walker", "0935921": "Dean Winters", "0004908": "Edie Falco", "0350079": "Luis Guzm\u00e1n", "0472762": "Olek Krupa", "0546797": "Mark Margolis", "0005221": "Christopher Meloni", "0604420": "George Morfogen", "0904967": "Luna Lauren Velez", "0000703": "BD Wong", "0010999": "Granville Adams", "0054397": "Arija Bareikis", "0143779": "Philip Casnoff", "0167024": "Robert Clohessy", "0319121": "Seth Gilliam", "0334027": "Enid Graham", "0462735": "Frederick Koehler", "0546306": "Tom Mardirosian", "0196185": "Craig muMs Grant", "0412907": "J.D. Williams", "0936001": "Scott William Winters", "0018642": "Lexington Alexander", "2988520": "Timothy L. Brown", "0182809": "William Cote", "0225027": "Natascia Diaz", "0227151": "Carl DiMaggio", "0380022": "Juan Carlos Hern\u00e1ndez", "0394434": "Tim Hopper", "0399763": "Ernie Hudson Jr.", "0761024": "Otto Sanchez", "0890709": "Nelson Vasquez", "0957257": "Chuck Zito", "0016243": "Carlo Alban", "0021157": "Whitney Allen", "0037044": "Mike Arotsky", "0094453": "Steve Bonge", "8821213": "Georges Bridges", "0188981": "Douglas Crosby", "1120264": "Todd Etelson", "0318824": "Brett Gillen", "1106926": "Ra Hanna", "1268789": "Jose Hernandez Jr.", "0447028": "Peter James Kelsch", "0510947": "Robert Lin", "0576720": "Seth William Meier", "0579457": "Chazz Menendez", "0642567": "Mick O'Rourke", "0657207": "James Palacio", "0658864": "John Palumbo", "0703691": "Rohan Quine", "0720312": "Floyd Resnick", "0908244": "Sybyl Walker", "1627600": "Joel West", "0936549": "Steven Wishnoff"}, "geners": ["Crime", "Drama", "Thriller"], "runtimes": ["59"],  "plot": ["Wangler 'finds out' his wife and her lover were murdered execution-style. Meanwhile, Poet and Pierce get burned by Hernandez, Ricardo and Guerra. Lockdown ensues, and Wangler finds himself vulnerable--and in a cell with Adebisi."], "genres": "N/A", "imdbID": "0668326", "rating": 8.3, "votes": 2122, "number_of_episodes": 56}