{"cast": {"0355910": "Michael C. Hall", "0004748": "Julie Benz", "1358539": "Jennifer Carpenter", "0454701": "Erik King", "0904967": "Luna Lauren Velez", "0953882": "David Zayas", "0001664": "James Remar", "0682762": "Geoff Pierson", "0553020": "Rudolf Martin", "0372958": "Gina Hecht", "0377034": "Brad William Henke", "0936001": "Scott William Winters", "1851416": "Dominic Janes", "0006439": "Erin Daniels", "1010931": "Monique Gabriela Curnen", "0023130": "Angela Alvarado", "2247732": "Christina Robinson", "2288060": "Daniel Goldman", "1404824": "Laura Marano", "1984458": "Devon Graye", "1051295": "Hunter King", "0121620": "Carlease Burke", "0491627": "Kathrin Middleton", "0923282": "Alex Wexo", "0895666": "Francisco Viana", "1190373": "Ashton Moio", "0558585": "Connor Matheus", "0570915": "Alden McKay", "1470289": "Elena Maria Garcia", "1892730": "Krista Swan", "6858425": "Patrick Bradford", "3566298": "Angel Luis Hern\u00e1ndez", "0391595": "Bruce Holman", "2701263": "Chad Jamian", "2869714": "Wendy Lee", "1616882": "Germ\u00e1n Legarreta", "2369021": "Nicholas Simmons", "2374606": "Frank Tedesco"}, "geners": ["Crime", "Drama", "Mystery", "Thriller"], "runtimes": ["58"],  "plot": ["The Ice Truck Killer begins leaving body parts from his victims at sites that relate to memories from Dexter's childhood, forcing him to confront his dark personal history."], "genres": "N/A", "imdbID": "0824887", "rating": 8.6, "votes": 9802, "number_of_episodes": 96}