{"cast": {"1056659": "John Oliver", "0443286": "David Kaye", "3134416": "Peter Daniel Straus", "0874339": "Donald Trump", "8577419": "JD Vance"}, "geners": ["Comedy", "News", "Talk-Show"], "runtimes": 0,  "plot": ["John Oliver explores challenges faced by disabled Americans seeking government benefits, highlights strict rules that remove people from programs, and offers suggestions to improve the disability benefits system.", "John Oliver talks about various obstacles in the way of receiving disability benefits by the US citizens. Also, how it easily kicks out people out of the program based on some strict rules and regulations. He also gave some suggestions to sort some of the issues in safety program.\u2014Niaz Islam Arif"], "genres": "N/A", "imdbID": "33383991", "rating": 7.6, "votes": 187, "number_of_episodes": 384}