{"cast": {"7802961": "Mayur More", "6845062": "Jitendra Kumar", "6845060": "Ranjan Raj", "10609388": "Urvi Singh", "6875641": "Arun Kumar", "0592790": "Loveleen Mishra", "8311745": "Jasmeet Singh Bhatia", "6449658": "Shivankit Singh Parihar", "10011377": "Gaurav Mishra", "7287295": "Alam Khan", "1741856": "Ahsaas Channa", "10319781": "Harish Peddinti", "10628438": "Avi Singh", "10593584": "Divya Kharnare", "10628442": "Bhavya Dutt", "9577367": "Sachin Viddrrohi", "10660201": "Rishabh Raj Sharma", "10261101": "Poojan Chhabra", "10660202": "Sachin Rana", "10660203": "Vineet Khatri", "10681433": "Samarth Shandilya", "0796513": "Sadiya Siddiqui"}, "geners": ["Comedy", "Drama"], "runtimes": ["37"],  "plot": ["There may be several paths to manufacture a product. But are the processes followed utilizing the resources optimally? Is the path followed that of least resistance?"], "genres": "N/A", "imdbID": "10228080", "rating": 8.7, "votes": 1504, "number_of_episodes": 15}